plover_syllabic_chording/__init__.py
plover_syllabic_chording/dictionary.py
plover_syllabic_chording/extension.py
plover_syllabic_chording/meta.py
plover_syllabic_chording/strokes.py
plover_syllabic_chording/system.py
plover_syllabic_chording/assets/syc_commands.syc
plover_syllabic_chording/assets/syc_dutch_basic.syc
plover_syllabic_chording/assets/syc_dutch_pro.syc
plover_syllabic_chording/assets/syc_english_basic.syc
plover_syllabic_chording/assets/syc_english_pro.syc
plover_syllabic_chording/assets/syc_modifiers.syc
plover_syllabic_chording/assets/syc_symbols.syc
plover_syllabic_chording/assets/syc_user.syc
plover_syllabic_chording-0.3.1.dist-info/LICENSE
plover_syllabic_chording-0.3.1.dist-info/METADATA
plover_syllabic_chording-0.3.1.dist-info/WHEEL
plover_syllabic_chording-0.3.1.dist-info/entry_points.txt
plover_syllabic_chording-0.3.1.dist-info/top_level.txt
plover_syllabic_chording-0.3.1.dist-info/zip-safe
plover_syllabic_chording-0.3.1.dist-info/RECORD
