Metadata-Version: 2.1
Name: plover-syllabic-chording
Version: 0.3.1
Summary: Syllabic Chording support for Plover
Home-page: https://github.com/AlexandraAlter/plover_syllabic_chording
Author: AlexandraAlter
Author-email: alexandra.alter@protonmail.com
License: The Unlicense (Unlicense)
Project-URL: Changelog, https://github.com/AlexandraAlter/plover_syllabic_chording/blob/master/NEWS.md
Project-URL: Source Code, https://github.com/AlexandraAlter/plover_syllabic_chording
Project-URL: Issue Tracker, https://github.com/AlexandraAlter/plover_syllabic_chording/issues
Keywords: plover plover_plugin
Platform: UNKNOWN
Classifier: Development Status :: 3 - Alpha
Classifier: Environment :: Plugins
Classifier: Intended Audience :: End Users/Desktop
Classifier: License :: OSI Approved :: The Unlicense (Unlicense)
Classifier: Operating System :: OS Independent
Classifier: Programming Language :: Python :: 3
Classifier: Programming Language :: Python :: 3.8
Requires-Python: >=3.8
Requires-Dist: plover (>=4.0.0.dev1)
Requires-Dist: bitstring (>=3.1.7)
